[
  {
    "message": "file:///home/runner/work/playground-tester/playground-tester/node_modules/@wp-playground/cli/index.js:237\n        throw new Error(y, { cause: u });\n              ^\n",
    "level": "FATAL",
    "type": "PLAYGROUND",
    "test": "ast-sqlite-boot",
    "plugin": "video-icon",
    "details": "file:///home/runner/work/playground-tester/playground-tester/node_modules/@wp-playground/cli/index.js:237\n        throw new Error(y, { cause: u });\n              ^\n",
    "log": "/tmp/tmp.KhjwZM05Jo"
  },
  {
    "message": "file:///home/runner/work/playground-tester/playground-tester/node_modules/@wp-playground/cli/index.js:237\n        throw new Error(y, { cause: u });\n              ^\n",
    "level": "FATAL",
    "type": "PLAYGROUND",
    "test": "asyncify-boot",
    "plugin": "video-icon",
    "details": "file:///home/runner/work/playground-tester/playground-tester/node_modules/@wp-playground/cli/index.js:237\n        throw new Error(y, { cause: u });\n              ^\n",
    "log": "/tmp/tmp.JDiR155k5e"
  },
  {
    "message": "file:///home/runner/work/playground-tester/playground-tester/node_modules/@wp-playground/cli/index.js:237\n        throw new Error(y, { cause: u });\n              ^\n",
    "level": "FATAL",
    "type": "PLAYGROUND",
    "test": "jspi-boot",
    "plugin": "video-icon",
    "details": "file:///home/runner/work/playground-tester/playground-tester/node_modules/@wp-playground/cli/index.js:237\n        throw new Error(y, { cause: u });\n              ^\n",
    "log": "/tmp/tmp.2r8c4v4KHu"
  }
]
