[
  {
    "message": "file:///home/runner/work/playground-tester/playground-tester/node_modules/@wp-playground/cli/run-cli-j-geJYS3.js:325\n        throw new Error($, { cause: h });\n              ^\n",
    "level": "FATAL",
    "type": "PLAYGROUND",
    "test": "ast-sqlite-boot",
    "plugin": "zakaat-calculator",
    "details": "file:///home/runner/work/playground-tester/playground-tester/node_modules/@wp-playground/cli/run-cli-j-geJYS3.js:325\n        throw new Error($, { cause: h });\n              ^\n",
    "log": "/tmp/tmp.5K6VanB02I"
  },
  {
    "message": "[19-Jun-2025 08:58:37 UTC] WordPres\n",
    "level": "INFO",
    "type": "OTHER",
    "test": "ast-sqlite-boot",
    "plugin": "zakaat-calculator",
    "details": "[19-Jun-2025 08:58:37 UTC] WordPres\n",
    "log": "/logs/plugins/z/zakaat-calculator/error.json"
  },
  {
    "message": "file:///home/runner/work/playground-tester/playground-tester/node_modules/@wp-playground/cli/run-cli-j-geJYS3.js:325\n        throw new Error($, { cause: h });\n              ^\n",
    "level": "FATAL",
    "type": "PLAYGROUND",
    "test": "asyncify-boot",
    "plugin": "zakaat-calculator",
    "details": "file:///home/runner/work/playground-tester/playground-tester/node_modules/@wp-playground/cli/run-cli-j-geJYS3.js:325\n        throw new Error($, { cause: h });\n              ^\n",
    "log": "/tmp/tmp.ehDh2lh4qS"
  },
  {
    "message": "[19-Jun-2025 08:58:37 UTC] WordPres\n",
    "level": "INFO",
    "type": "OTHER",
    "test": "asyncify-boot",
    "plugin": "zakaat-calculator",
    "details": "[19-Jun-2025 08:58:37 UTC] WordPres\n",
    "log": "/logs/plugins/z/zakaat-calculator/error.json"
  },
  {
    "message": "file:///home/runner/work/playground-tester/playground-tester/node_modules/@wp-playground/cli/run-cli-j-geJYS3.js:325\n        throw new Error($, { cause: h });\n              ^\n",
    "level": "FATAL",
    "type": "PLAYGROUND",
    "test": "jspi-boot",
    "plugin": "zakaat-calculator",
    "details": "file:///home/runner/work/playground-tester/playground-tester/node_modules/@wp-playground/cli/run-cli-j-geJYS3.js:325\n        throw new Error($, { cause: h });\n              ^\n",
    "log": "/tmp/tmp.pjWqPsyRBq"
  },
  {
    "message": "[19-Jun-2025 08:58:37 UTC] WordPres\n",
    "level": "INFO",
    "type": "OTHER",
    "test": "jspi-boot",
    "plugin": "zakaat-calculator",
    "details": "[19-Jun-2025 08:58:37 UTC] WordPres\n",
    "log": "/logs/plugins/z/zakaat-calculator/error.json"
  }
]
